FPGA/DE2_115_sopcbuilder_12/sensor/hdl/sram_controller.v
///
/// Internal memory controller
/// --------------------------
///
/// This module contol writes and read data to internal SDRAM from binary data
/// send from camera throught to the threshold block.
///
/// .. figure:: sram_controller.png
///
///    SRAM controller block
///
/// It writes serial two bits data in internal SRAM of 32 bits word and it 
/// reads that words and send serial data to external SDRAM.
///
module sram_controller ( 
        input clock,
        input reset_n,
        // Parameters
        input [22:0] image_size,
        input [12:0] image_start_addr,
        // External data input
        input write_image_en,
        input write_image,
        input [1:0] write_image_data,
        output write_image_done,
        // External data output
        input read_image_en,
        output read_image,
        output reg [1:0] read_image_data,
        output read_image_done,
        // SRAM signals
        output sram_clock,
        output sram_write,
        output [31:0] sram_write_data,
        output [12:0] sram_write_addr,
        input [31:0] sram_read_data,
        output [12:0] sram_read_addr
    );
    
    // Reset control
    reg [12:0] image_size_addr;
    always @(posedge clock)
    begin
        if (!reset_n) begin
            image_size_addr[12:0] <= image_size[12:0] + image_start_addr[12:0];
        end
    end
    
    // Write control
    reg write;
    reg [12:0] write_addr;
    reg [31:0] w_data;
    reg [31:0] write_data;
    reg write_done;
    reg [31:0] wi;
    always @(posedge clock)
    begin
        if (write_image_en) begin
            if (write_image && !write_done) begin
                case (wi[3:0])
                    0: w_data[1:0] <= write_image_data[1:0];
                    1: w_data[3:2] <= write_image_data[1:0];
                    2: w_data[5:4] <= write_image_data[1:0];
                    3: w_data[7:6] <= write_image_data[1:0];
                    4: w_data[9:8] <= write_image_data[1:0];
                    5: w_data[11:10] <= write_image_data[1:0];
                    6: w_data[13:12] <= write_image_data[1:0];
                    7: w_data[15:14] <= write_image_data[1:0];
                    8: w_data[17:16] <= write_image_data[1:0];
                    9: w_data[19:18] <= write_image_data[1:0];
                    10: w_data[21:20] <= write_image_data[1:0];
                    11: w_data[23:22] <= write_image_data[1:0];
                    12: w_data[25:24] <= write_image_data[1:0];
                    13: w_data[27:26] <= write_image_data[1:0];
                    14: w_data[29:28] <= write_image_data[1:0];
                    15: write_data[31:0] <= {write_image_data[1:0],
                                             w_data[29:0]};
                endcase
                if (wi > 15) begin
                    if (wi[3:0] == 0) begin
                        write_addr[12:0] <= write_addr[12:0] + 13'd1;
                    end
                end
                if (wi[3:0] == 15) begin
                    write <= 1'b1;
                    if (write_addr[12:0] == (image_size_addr[12:0] - 1)) begin
                        write_done <= 1'b1;
                    end
                end
                else begin
                    write <= 1'b0;
                end
                wi <= wi + 1;
            end
            else begin
                write <= 1'b0;
            end
        end
        else begin
            wi <= 0;
            write <= 1'b0;
            write_addr[12:0] <= image_start_addr[12:0];
            write_data[31:0] <= 32'd0;
            write_done <= 1'b0;
        end
    end
    
    assign write_image_done = write_done;
    	
    // Read control
    reg read;
    reg [12:0] read_addr;
    reg [31:0] read_data;
    reg read_done;
    reg [31:0] ri;	    
    always @(posedge clock)
    begin
        if (read_image_en) begin
            if (!read_done) begin
                case (ri[4:0])
                    0: read_image_data[1:0] <= read_data[1:0];
                    1: read_image_data[1:0] <= read_data[3:2];
                    2: read_image_data[1:0] <= read_data[5:4];
                    3: read_image_data[1:0] <= read_data[7:6];
                    4: read_image_data[1:0] <= read_data[9:8];
                    5: read_image_data[1:0] <= read_data[11:10];
                    6: read_image_data[1:0] <= read_data[13:12];
                    7: read_image_data[1:0] <= read_data[15:14];
                    8: read_image_data[1:0] <= read_data[17:16];
                    9: read_image_data[1:0] <= read_data[19:18];
                    10: read_image_data[1:0] <= read_data[21:20];
                    11: read_image_data[1:0] <= read_data[23:22];
                    12: read_image_data[1:0] <= read_data[25:24];
                    13: read_image_data[1:0] <= read_data[27:26];
                    14: read_image_data[1:0] <= read_data[29:28];
                    15: read_image_data[1:0] <= read_data[31:30];
                endcase
                if (ri[4:0] < 16) begin
                    if (ri[3:0] == 0) begin
                        read_addr[12:0] <= read_addr[12:0] + 13'd1;
                    end
                    ri <= ri + 1;
                    read <= 1'b1;
                end
                else begin
                    // -- ADDED --
                    if (ri < 31) begin
                        ri <= ri + 1;
                    end
                    else begin
                        ri <= 0;
                    end
                    // -----------
                    //ri <= 0;
                    read <= 1'b0;
                    read_data[31:0] <= sram_read_data[31:0];
                    if (read_addr[12:0] == image_size_addr[12:0]) begin
                        read_done <= 1'b1;
                    end
                end
            end
            else begin
                read <= 1'b0;
            end
        end
        else begin
            ri <= 0;
            read <= 1'b0;
            read_addr[12:0] <= image_start_addr[12:0];
            read_data[31:0] <= sram_read_data[31:0];
            read_done <= 1'b0;
        end
    end
    
    assign read_image = read;
    assign read_image_done = read_done;

    // SRAM control signals
    assign sram_clock = clock;
    assign sram_write = write;
    assign sram_write_data[31:0] = write_data[31:0];
    assign sram_write_addr[12:0] = write_addr[12:0];
    assign sram_read_addr[12:0] = read_addr[12:0];
        
endmodule

FPGA/DE2_115_sopcbuilder_12/sensor/test/sram_controller_tb.v
`timescale 1 ns / 100 ps

module sram_controller_tb;
    
    reg clock;
    reg reset_n;
    
    reg write_en;
    reg read_en;
    
    wire write_done;
    wire read_done;
    
    reg write;
    reg [1:0] write_data;
    
    wire read;
    wire [1:0] read_data;
    
    wire sram_clock;
    wire sram_write;
    wire [31:0] sram_write_data;
    wire [12:0] sram_write_addr;
    reg [31:0] sram_read_data;
    wire [12:0] sram_read_addr;
    
    sram_controller sram_ctrl (
        .clock(clock),
        .reset_n(reset_n),
        // Parameters
        .image_size(23'd64),
        .image_start_addr(13'd0),
        // External data input
        .write_image_en(write_en),
        .write_image(write),
        .write_image_data(write_data[1:0]),
        .write_image_done(write_done),
        // External data output
        .read_image_en(read_en),
        .read_image(read),
        .read_image_data(read_data[1:0]),
        .read_image_done(read_done),
        // SRAM signals
        .sram_clock(sram_clock),
        .sram_write(sram_write),
        .sram_write_data(sram_write_data[31:0]),
        .sram_write_addr(sram_write_addr[12:0]),
        .sram_read_data(sram_read_data[31:0]),
        .sram_read_addr(sram_read_addr[12:0])
    );
    
    initial clock = 1'b0;
    always #5 clock = ~clock;
    
    initial reset_n = 1'b0;
    initial #100 reset_n = 1'b1;
    
    initial write_en = 1'b0;
    initial #150 write_en = 1'b1;
    initial write = 1'b0;
    
    initial read_en = 1'b0;
    initial sram_read_data = 32'h99999999;
        
    integer i = 0;
    always @(posedge clock)
    begin
        if (reset_n) begin
            if (write_en) begin
                write <= 1'b1;
	            write_data[1:0] <= i[1:0];
	            if (i < 64) begin
	                i <= i + 1;
	            end
	            else begin
	                write_en <= 1'b0;
	                read_en <= 1'b1;
	            end
	        end
	    end
    end
    
    initial $dumpvars;
    initial #1500 $finish;

endmodule

FPGA/DE2_115_sopcbuilder_12/sensor/sim/sram_controller_tb.vcd
$date
	Tue May 17 16:15:54 2011
$end
$version
	Icarus Verilog
$end
$timescale
	100ps
$end
$scope module sram_controller_tb $end
$var wire 1 ! read $end
$var wire 2 " read_data [1:0] $end
$var wire 1 # read_done $end
$var wire 1 $ sram_clock $end
$var wire 13 % sram_read_addr [12:0] $end
$var wire 1 & sram_write $end
$var wire 13 ' sram_write_addr [12:0] $end
$var wire 32 ( sram_write_data [31:0] $end
$var wire 1 ) write_done $end
$var reg 1 * clock $end
$var integer 32 + i [31:0] $end
$var reg 1 , read_en $end
$var reg 1 - reset_n $end
$var reg 32 . sram_read_data [31:0] $end
$var reg 1 / write $end
$var reg 2 0 write_data [1:0] $end
$var reg 1 1 write_en $end
$scope module sram_ctrl $end
$var wire 1 2 clock $end
$var wire 23 3 image_size [22:0] $end
$var wire 13 4 image_start_addr [12:0] $end
$var wire 1 ! read_image $end
$var wire 1 # read_image_done $end
$var wire 1 5 read_image_en $end
$var wire 1 6 reset_n $end
$var wire 1 $ sram_clock $end
$var wire 13 7 sram_read_addr [12:0] $end
$var wire 32 8 sram_read_data [31:0] $end
$var wire 1 & sram_write $end
$var wire 13 9 sram_write_addr [12:0] $end
$var wire 32 : sram_write_data [31:0] $end
$var wire 1 ; write_image $end
$var wire 2 < write_image_data [1:0] $end
$var wire 1 ) write_image_done $end
$var wire 1 = write_image_en $end
$var reg 13 > image_size_addr [12:0] $end
$var reg 1 ? read $end
$var reg 13 @ read_addr [12:0] $end
$var reg 32 A read_data [31:0] $end
$var reg 1 B read_done $end
$var reg 2 C read_image_data [1:0] $end
$var reg 32 D ri [31:0] $end
$var reg 32 E w_data [31:0] $end
$var reg 32 F wi [31:0] $end
$var reg 1 G write $end
$var reg 13 H write_addr [12:0] $end
$var reg 32 I write_data [31:0] $end
$var reg 1 J write_done $end
$upscope $end
$upscope $end
$enddefinitions $end
#0
$dumpvars
xJ
bx I
bx H
xG
bx F
bx E
bx D
bx C
xB
bx A
bx @
x?
bx >
0=
bx <
0;
bx :
bx 9
b10011001100110011001100110011001 8
bx 7
06
05
b0 4
b1000000 3
02
01
bx 0
0/
b10011001100110011001100110011001 .
0-
0,
b0 +
0*
x)
bx (
bx '
x&
bx %
0$
x#
bx "
x!
$end
#50
b100 >
0J
0)
b0 I
b0 (
b0 :
b0 H
b0 '
b0 9
0G
0&
b0 F
0B
0#
b10011001100110011001100110011001 A
b0 @
b0 %
b0 7
0?
0!
b0 D
1*
1$
12
#100
0*
0$
02
#150
1*
1$
12
#200
0*
0$
02
#250
1*
1$
12
#300
0*
0$
02
#350
1*
1$
12
#400
0*
0$
02
#450
1*
1$
12
#500
0*
0$
02
#550
1*
1$
12
#600
0*
0$
02
#650
1*
1$
12
#700
0*
0$
02
#750
1*
1$
12
#800
0*
0$
02
#850
1*
1$
12
#900
0*
0$
02
#950
1*
1$
12
#1000
0*
0$
02
1-
16
#1050
1*
1$
12
#1100
0*
0$
02
#1150
1*
1$
12
#1200
0*
0$
02
#1250
1*
1$
12
#1300
0*
0$
02
#1350
1*
1$
12
#1400
0*
0$
02
#1450
1*
1$
12
#1500
0*
0$
02
11
1=
#1550
b1 +
b0 0
b0 <
1/
1;
1*
1$
12
#1600
0*
0$
02
#1650
b1 F
bx00 E
b10 +
b1 0
b1 <
1*
1$
12
#1700
0*
0$
02
#1750
b11 +
b10 0
b10 <
b10 F
bx0100 E
1*
1$
12
#1800
0*
0$
02
#1850
b11 F
bx100100 E
b100 +
b11 0
b11 <
1*
1$
12
#1900
0*
0$
02
#1950
b101 +
b0 0
b0 <
b100 F
bx11100100 E
1*
1$
12
#2000
0*
0$
02
#2050
b101 F
bx0011100100 E
b110 +
b1 0
b1 <
1*
1$
12
#2100
0*
0$
02
#2150
b111 +
b10 0
b10 <
b110 F
bx010011100100 E
1*
1$
12
#2200
0*
0$
02
#2250
b111 F
bx10010011100100 E
b1000 +
b11 0
b11 <
1*
1$
12
#2300
0*
0$
02
#2350
b1001 +
b0 0
b0 <
b1000 F
bx1110010011100100 E
1*
1$
12
#2400
0*
0$
02
#2450
b1001 F
bx001110010011100100 E
b1010 +
b1 0
b1 <
1*
1$
12
#2500
0*
0$
02
#2550
b1011 +
b10 0
b10 <
b1010 F
bx01001110010011100100 E
1*
1$
12
#2600
0*
0$
02
#2650
b1011 F
bx1001001110010011100100 E
b1100 +
b11 0
b11 <
1*
1$
12
#2700
0*
0$
02
#2750
b1101 +
b0 0
b0 <
b1100 F
bx111001001110010011100100 E
1*
1$
12
#2800
0*
0$
02
#2850
b1101 F
bx00111001001110010011100100 E
b1110 +
b1 0
b1 <
1*
1$
12
#2900
0*
0$
02
#2950
b1111 +
b10 0
b10 <
b1110 F
bx0100111001001110010011100100 E
1*
1$
12
#3000
0*
0$
02
#3050
b1111 F
bx100100111001001110010011100100 E
b10000 +
b11 0
b11 <
1*
1$
12
#3100
0*
0$
02
#3150
b10001 +
b0 0
b0 <
b10000 F
1G
1&
b11100100111001001110010011100100 I
b11100100111001001110010011100100 (
b11100100111001001110010011100100 :
1*
1$
12
#3200
0*
0$
02
#3250
b10001 F
0G
0&
b1 H
b1 '
b1 9
bx100100111001001110010011100100 E
b10010 +
b1 0
b1 <
1*
1$
12
#3300
0*
0$
02
#3350
b10011 +
b10 0
b10 <
b10010 F
bx100100111001001110010011100100 E
1*
1$
12
#3400
0*
0$
02
#3450
b10011 F
bx100100111001001110010011100100 E
b10100 +
b11 0
b11 <
1*
1$
12
#3500
0*
0$
02
#3550
b10101 +
b0 0
b0 <
b10100 F
bx100100111001001110010011100100 E
1*
1$
12
#3600
0*
0$
02
#3650
b10101 F
bx100100111001001110010011100100 E
b10110 +
b1 0
b1 <
1*
1$
12
#3700
0*
0$
02
#3750
b10111 +
b10 0
b10 <
b10110 F
bx100100111001001110010011100100 E
1*
1$
12
#3800
0*
0$
02
#3850
b10111 F
bx100100111001001110010011100100 E
b11000 +
b11 0
b11 <
1*
1$
12
#3900
0*
0$
02
#3950
b11001 +
b0 0
b0 <
b11000 F
bx100100111001001110010011100100 E
1*
1$
12
#4000
0*
0$
02
#4050
b11001 F
bx100100111001001110010011100100 E
b11010 +
b1 0
b1 <
1*
1$
12
#4100
0*
0$
02
#4150
b11011 +
b10 0
b10 <
b11010 F
bx100100111001001110010011100100 E
1*
1$
12
#4200
0*
0$
02
#4250
b11011 F
bx100100111001001110010011100100 E
b11100 +
b11 0
b11 <
1*
1$
12
#4300
0*
0$
02
#4350
b11101 +
b0 0
b0 <
b11100 F
bx100100111001001110010011100100 E
1*
1$
12
#4400
0*
0$
02
#4450
b11101 F
bx100100111001001110010011100100 E
b11110 +
b1 0
b1 <
1*
1$
12
#4500
0*
0$
02
#4550
b11111 +
b10 0
b10 <
b11110 F
bx100100111001001110010011100100 E
1*
1$
12
#4600
0*
0$
02
#4650
b11111 F
bx100100111001001110010011100100 E
b100000 +
b11 0
b11 <
1*
1$
12
#4700
0*
0$
02
#4750
b100001 +
b0 0
b0 <
b100000 F
1G
1&
1*
1$
12
#4800
0*
0$
02
#4850
b100001 F
0G
0&
b10 H
b10 '
b10 9
bx100100111001001110010011100100 E
b100010 +
b1 0
b1 <
1*
1$
12
#4900
0*
0$
02
#4950
b100011 +
b10 0
b10 <
b100010 F
bx100100111001001110010011100100 E
1*
1$
12
#5000
0*
0$
02
#5050
b100011 F
bx100100111001001110010011100100 E
b100100 +
b11 0
b11 <
1*
1$
12
#5100
0*
0$
02
#5150
b100101 +
b0 0
b0 <
b100100 F
bx100100111001001110010011100100 E
1*
1$
12
#5200
0*
0$
02
#5250
b100101 F
bx100100111001001110010011100100 E
b100110 +
b1 0
b1 <
1*
1$
12
#5300
0*
0$
02
#5350
b100111 +
b10 0
b10 <
b100110 F
bx100100111001001110010011100100 E
1*
1$
12
#5400
0*
0$
02
#5450
b100111 F
bx100100111001001110010011100100 E
b101000 +
b11 0
b11 <
1*
1$
12
#5500
0*
0$
02
#5550
b101001 +
b0 0
b0 <
b101000 F
bx100100111001001110010011100100 E
1*
1$
12
#5600
0*
0$
02
#5650
b101001 F
bx100100111001001110010011100100 E
b101010 +
b1 0
b1 <
1*
1$
12
#5700
0*
0$
02
#5750
b101011 +
b10 0
b10 <
b101010 F
bx100100111001001110010011100100 E
1*
1$
12
#5800
0*
0$
02
#5850
b101011 F
bx100100111001001110010011100100 E
b101100 +
b11 0
b11 <
1*
1$
12
#5900
0*
0$
02
#5950
b101101 +
b0 0
b0 <
b101100 F
bx100100111001001110010011100100 E
1*
1$
12
#6000
0*
0$
02
#6050
b101101 F
bx100100111001001110010011100100 E
b101110 +
b1 0
b1 <
1*
1$
12
#6100
0*
0$
02
#6150
b101111 +
b10 0
b10 <
b101110 F
bx100100111001001110010011100100 E
1*
1$
12
#6200
0*
0$
02
#6250
b101111 F
bx100100111001001110010011100100 E
b110000 +
b11 0
b11 <
1*
1$
12
#6300
0*
0$
02
#6350
b110001 +
b0 0
b0 <
b110000 F
1G
1&
1*
1$
12
#6400
0*
0$
02
#6450
b110001 F
0G
0&
b11 H
b11 '
b11 9
bx100100111001001110010011100100 E
b110010 +
b1 0
b1 <
1*
1$
12
#6500
0*
0$
02
#6550
b110011 +
b10 0
b10 <
b110010 F
bx100100111001001110010011100100 E
1*
1$
12
#6600
0*
0$
02
#6650
b110011 F
bx100100111001001110010011100100 E
b110100 +
b11 0
b11 <
1*
1$
12
#6700
0*
0$
02
#6750
b110101 +
b0 0
b0 <
b110100 F
bx100100111001001110010011100100 E
1*
1$
12
#6800
0*
0$
02
#6850
b110101 F
bx100100111001001110010011100100 E
b110110 +
b1 0
b1 <
1*
1$
12
#6900
0*
0$
02
#6950
b110111 +
b10 0
b10 <
b110110 F
bx100100111001001110010011100100 E
1*
1$
12
#7000
0*
0$
02
#7050
b110111 F
bx100100111001001110010011100100 E
b111000 +
b11 0
b11 <
1*
1$
12
#7100
0*
0$
02
#7150
b111001 +
b0 0
b0 <
b111000 F
bx100100111001001110010011100100 E
1*
1$
12
#7200
0*
0$
02
#7250
b111001 F
bx100100111001001110010011100100 E
b111010 +
b1 0
b1 <
1*
1$
12
#7300
0*
0$
02
#7350
b111011 +
b10 0
b10 <
b111010 F
bx100100111001001110010011100100 E
1*
1$
12
#7400
0*
0$
02
#7450
b111011 F
bx100100111001001110010011100100 E
b111100 +
b11 0
b11 <
1*
1$
12
#7500
0*
0$
02
#7550
b111101 +
b0 0
b0 <
b111100 F
bx100100111001001110010011100100 E
1*
1$
12
#7600
0*
0$
02
#7650
b111101 F
bx100100111001001110010011100100 E
b111110 +
b1 0
b1 <
1*
1$
12
#7700
0*
0$
02
#7750
b111111 +
b10 0
b10 <
b111110 F
bx100100111001001110010011100100 E
1*
1$
12
#7800
0*
0$
02
#7850
b111111 F
bx100100111001001110010011100100 E
b1000000 +
b11 0
b11 <
1*
1$
12
#7900
0*
0$
02
#7950
1,
15
01
0=
b0 0
b0 <
b1000000 F
1J
1)
1G
1&
1*
1$
12
#8000
0*
0$
02
#8050
0J
0)
b0 I
b0 (
b0 :
b0 H
b0 '
b0 9
0G
0&
b0 F
1?
1!
b1 D
b1 @
b1 %
b1 7
b1 C
b1 "
1*
1$
12
#8100
0*
0$
02
#8150
b10 D
b10 C
b10 "
1*
1$
12
#8200
0*
0$
02
#8250
b11 D
b1 C
b1 "
1*
1$
12
#8300
0*
0$
02
#8350
b100 D
b10 C
b10 "
1*
1$
12
#8400
0*
0$
02
#8450
b101 D
b1 C
b1 "
1*
1$
12
#8500
0*
0$
02
#8550
b110 D
b10 C
b10 "
1*
1$
12
#8600
0*
0$
02
#8650
b111 D
b1 C
b1 "
1*
1$
12
#8700
0*
0$
02
#8750
b1000 D
b10 C
b10 "
1*
1$
12
#8800
0*
0$
02
#8850
b1001 D
b1 C
b1 "
1*
1$
12
#8900
0*
0$
02
#8950
b1010 D
b10 C
b10 "
1*
1$
12
#9000
0*
0$
02
#9050
b1011 D
b1 C
b1 "
1*
1$
12
#9100
0*
0$
02
#9150
b1100 D
b10 C
b10 "
1*
1$
12
#9200
0*
0$
02
#9250
b1101 D
b1 C
b1 "
1*
1$
12
#9300
0*
0$
02
#9350
b1110 D
b10 C
b10 "
1*
1$
12
#9400
0*
0$
02
#9450
b1111 D
b1 C
b1 "
1*
1$
12
#9500
0*
0$
02
#9550
b10000 D
b10 C
b10 "
1*
1$
12
#9600
0*
0$
02
#9650
0?
0!
b0 D
1*
1$
12
#9700
0*
0$
02
#9750
1?
1!
b1 D
b10 @
b10 %
b10 7
b1 C
b1 "
1*
1$
12
#9800
0*
0$
02
#9850
b10 D
b10 C
b10 "
1*
1$
12
#9900
0*
0$
02
#9950
b11 D
b1 C
b1 "
1*
1$
12
#10000
0*
0$
02
#10050
b100 D
b10 C
b10 "
1*
1$
12
#10100
0*
0$
02
#10150
b101 D
b1 C
b1 "
1*
1$
12
#10200
0*
0$
02
#10250
b110 D
b10 C
b10 "
1*
1$
12
#10300
0*
0$
02
#10350
b111 D
b1 C
b1 "
1*
1$
12
#10400
0*
0$
02
#10450
b1000 D
b10 C
b10 "
1*
1$
12
#10500
0*
0$
02
#10550
b1001 D
b1 C
b1 "
1*
1$
12
#10600
0*
0$
02
#10650
b1010 D
b10 C
b10 "
1*
1$
12
#10700
0*
0$
02
#10750
b1011 D
b1 C
b1 "
1*
1$
12
#10800
0*
0$
02
#10850
b1100 D
b10 C
b10 "
1*
1$
12
#10900
0*
0$
02
#10950
b1101 D
b1 C
b1 "
1*
1$
12
#11000
0*
0$
02
#11050
b1110 D
b10 C
b10 "
1*
1$
12
#11100
0*
0$
02
#11150
b1111 D
b1 C
b1 "
1*
1$
12
#11200
0*
0$
02
#11250
b10000 D
b10 C
b10 "
1*
1$
12
#11300
0*
0$
02
#11350
0?
0!
b0 D
1*
1$
12
#11400
0*
0$
02
#11450
1?
1!
b1 D
b11 @
b11 %
b11 7
b1 C
b1 "
1*
1$
12
#11500
0*
0$
02
#11550
b10 D
b10 C
b10 "
1*
1$
12
#11600
0*
0$
02
#11650
b11 D
b1 C
b1 "
1*
1$
12
#11700
0*
0$
02
#11750
b100 D
b10 C
b10 "
1*
1$
12
#11800
0*
0$
02
#11850
b101 D
b1 C
b1 "
1*
1$
12
#11900
0*
0$
02
#11950
b110 D
b10 C
b10 "
1*
1$
12
#12000
0*
0$
02
#12050
b111 D
b1 C
b1 "
1*
1$
12
#12100
0*
0$
02
#12150
b1000 D
b10 C
b10 "
1*
1$
12
#12200
0*
0$
02
#12250
b1001 D
b1 C
b1 "
1*
1$
12
#12300
0*
0$
02
#12350
b1010 D
b10 C
b10 "
1*
1$
12
#12400
0*
0$
02
#12450
b1011 D
b1 C
b1 "
1*
1$
12
#12500
0*
0$
02
#12550
b1100 D
b10 C
b10 "
1*
1$
12
#12600
0*
0$
02
#12650
b1101 D
b1 C
b1 "
1*
1$
12
#12700
0*
0$
02
#12750
b1110 D
b10 C
b10 "
1*
1$
12
#12800
0*
0$
02
#12850
b1111 D
b1 C
b1 "
1*
1$
12
#12900
0*
0$
02
#12950
b10000 D
b10 C
b10 "
1*
1$
12
#13000
0*
0$
02
#13050
0?
0!
b0 D
1*
1$
12
#13100
0*
0$
02
#13150
1?
1!
b1 D
b100 @
b100 %
b100 7
b1 C
b1 "
1*
1$
12
#13200
0*
0$
02
#13250
b10 D
b10 C
b10 "
1*
1$
12
#13300
0*
0$
02
#13350
b11 D
b1 C
b1 "
1*
1$
12
#13400
0*
0$
02
#13450
b100 D
b10 C
b10 "
1*
1$
12
#13500
0*
0$
02
#13550
b101 D
b1 C
b1 "
1*
1$
12
#13600
0*
0$
02
#13650
b110 D
b10 C
b10 "
1*
1$
12
#13700
0*
0$
02
#13750
b111 D
b1 C
b1 "
1*
1$
12
#13800
0*
0$
02
#13850
b1000 D
b10 C
b10 "
1*
1$
12
#13900
0*
0$
02
#13950
b1001 D
b1 C
b1 "
1*
1$
12
#14000
0*
0$
02
#14050
b1010 D
b10 C
b10 "
1*
1$
12
#14100
0*
0$
02
#14150
b1011 D
b1 C
b1 "
1*
1$
12
#14200
0*
0$
02
#14250
b1100 D
b10 C
b10 "
1*
1$
12
#14300
0*
0$
02
#14350
b1101 D
b1 C
b1 "
1*
1$
12
#14400
0*
0$
02
#14450
b1110 D
b10 C
b10 "
1*
1$
12
#14500
0*
0$
02
#14550
b1111 D
b1 C
b1 "
1*
1$
12
#14600
0*
0$
02
#14650
b10000 D
b10 C
b10 "
1*
1$
12
#14700
0*
0$
02
#14750
1B
1#
0?
0!
b0 D
1*
1$
12
